MANIFEST.in
README.rst
README.txt
distribute_setup.py
fabfile.py
post.py
post_vagrant.py
setup.cfg
setup.py
pms/__init__.py
pms/aggregates.py
pms/app.py
pms/config.py
pms/connection.py
pms/watcher.py
pms.egg-info/PKG-INFO
pms.egg-info/SOURCES.txt
pms.egg-info/dependency_links.txt
pms.egg-info/entry_points.txt
pms.egg-info/not-zip-safe
pms.egg-info/requires.txt
pms.egg-info/top_level.txt
pms/static/events.js
pms/static/graph.js
pms/static/css/basic.css
pms/static/css/visualize-dark.css
pms/static/css/visualize-light.css
pms/static/css/visualize.css
pms/static/js/example.js
pms/static/js/excanvas.js
pms/static/js/excanvas.min.js
pms/static/js/jquery.colorhelpers.js
pms/static/js/jquery.colorhelpers.min.js
pms/static/js/jquery.flot.crosshair.js
pms/static/js/jquery.flot.crosshair.min.js
pms/static/js/jquery.flot.fillbetween.js
pms/static/js/jquery.flot.fillbetween.min.js
pms/static/js/jquery.flot.image.js
pms/static/js/jquery.flot.image.min.js
pms/static/js/jquery.flot.js
pms/static/js/jquery.flot.min.js
pms/static/js/jquery.flot.navigate.js
pms/static/js/jquery.flot.navigate.min.js
pms/static/js/jquery.flot.pie.js
pms/static/js/jquery.flot.pie.min.js
pms/static/js/jquery.flot.resize.js
pms/static/js/jquery.flot.resize.min.js
pms/static/js/jquery.flot.selection.js
pms/static/js/jquery.flot.selection.min.js
pms/static/js/jquery.flot.stack.js
pms/static/js/jquery.flot.stack.min.js
pms/static/js/jquery.flot.symbol.js
pms/static/js/jquery.flot.symbol.min.js
pms/static/js/jquery.flot.threshold.js
pms/static/js/jquery.flot.threshold.min.js
pms/static/js/jquery.js
pms/static/js/jquery.min.js
pms/static/js/visualize.jQuery.js
pms/static/shared/jquery.min.js
pms/static/shared/jqueryui.min.js
pms/templates/graph.jinja2