Metadata-Version: 1.0
Name: pms
Version: 0.1.6
Summary: An application monitoring service
Home-page: https://github.com/philipcristiano/pms
Author: Philip Cristiano
Author-email: pms@philipcristiano.com
License: BSD
Keywords: monitoring
Platform: UNKNOWN
